{
    "asset": {
        "format": "jpg",
        "id": "03496e13df8d4973be6e34261abfbd5a",
        "name": "00001450.jpg",
        "path": "file:C:/Users/trevo/PycharmProjects/TrainYourOwnYOLO-master/Data/Source_Images/Training_Images/00001450.jpg",
        "size": {
            "width": 874,
            "height": 492
        },
        "state": 2,
        "type": 1
    },
    "regions": [
        {
            "id": "aDnUQ0bQX",
            "type": "RECTANGLE",
            "tags": [
                "Helicopter"
            ],
            "boundingBox": {
                "height": 411.6820512820513,
                "width": 748.3020683020683,
                "left": 85.76046176046175,
                "top": 43.385096153846156
            },
            "points": [
                {
                    "x": 85.76046176046175,
                    "y": 43.385096153846156
                },
                {
                    "x": 834.0625300625301,
                    "y": 43.385096153846156
                },
                {
                    "x": 834.0625300625301,
                    "y": 455.0671474358974
                },
                {
                    "x": 85.76046176046175,
                    "y": 455.0671474358974
                }
            ]
        }
    ],
    "version": "2.2.0"
}