{
    "asset": {
        "format": "jpg",
        "id": "3f0f1ef1c0071c77416f1e9009e258b8",
        "name": "00001355.jpg",
        "path": "file:C:/Users/trevo/PycharmProjects/TrainYourOwnYOLO-master/Data/Source_Images/Training_Images/00001355.jpg",
        "size": {
            "width": 634,
            "height": 599
        },
        "state": 2,
        "type": 1
    },
    "regions": [
        {
            "id": "EMQZrnyP9",
            "type": "RECTANGLE",
            "tags": [
                "Helicopter"
            ],
            "boundingBox": {
                "height": 318.16043613707166,
                "width": 357.35393671817513,
                "left": 145.56137325239146,
                "top": 50.38317757009346
            },
            "points": [
                {
                    "x": 145.56137325239146,
                    "y": 50.38317757009346
                },
                {
                    "x": 502.91530997056657,
                    "y": 50.38317757009346
                },
                {
                    "x": 502.91530997056657,
                    "y": 368.54361370716515
                },
                {
                    "x": 145.56137325239146,
                    "y": 368.54361370716515
                }
            ]
        }
    ],
    "version": "2.2.0"
}